<?xml version="1.0" encoding="UTF-8"?>
<!--

 Author: Mo McRoberts <mo.mcroberts@bbc.co.uk>

 Copyright (c) 2014 BBC

  Licensed under the terms of the Open Government Licence, version 2.0.
  You may obtain a copy of the license at:

	https://www.nationalarchives.gov.uk/doc/open-government-licence/version/2/

-->
<legalnotice version="5.0" xml:lang="en-gb" xmlns="http://docbook.org/ns" xmlns:xinclude="http://www.w3.org/2001/XInclude" xmlns:xlink="http://www.w3.org/1999/xlink" xml:id="legal">
	<para>
		Copyright © 2014 BBC.
	</para>
	<para>
		The text of this book is licensed under the terms of the <citetitle><link xlink:href="http://www.nationalarchives.gov.uk/doc/open-government-licence/version/2/">Open Government Licence, v2.0</link></citetitle>.
	</para>
	<para>
		Accompanying code and samples are licensed under the terms of the <citetitle><link xlink:href="http://www.apache.org/licenses/LICENSE-2.0">Apache License, Version 2.0</link></citetitle>.
	</para>
</legalnotice>
